{
    "version": "7.30.5.2",
    "description": "BaiduNetdisk for Windows",
    "homepage": "https://pan.baidu.com/download#win",
    "license": "http://yun.baidu.com/disk/privacy",
    "url": "https://issuepcdn.baidupcs.com/issue/netdisk/yunguanjia/BaiduNetdisk_7.30.5.2.exe#/dl.7z",
    "hash": "10c8622bedeb1169ffda7c8ea27dfaeb0c24db421b0256f09fa6f85514486f70",
    "bin": "BaiduNetdisk.exe",
    "shortcuts": [
        [
            "BaiduNetdisk.exe",
            "BaiduNetdisk"
        ]
    ],
    "checkver": {
        "url": "https://yun.baidu.com/disk/cmsdata?platform=guanjia&page=1&num=2",
        "regex": "BaiduNetdisk_([\\d.]+).exe"
    },
    "autoupdate": {
        "url": "https://issuepcdn.baidupcs.com/issue/netdisk/yunguanjia/BaiduNetdisk_$version.exe#/dl.7z"
    },
    "notes": ""
}
