{
    "version": "7.59.5.104",
    "description": "BaiduNetdisk for Windows",
    "homepage": "https://pan.baidu.com/download#win",
    "license": "http://yun.baidu.com/disk/privacy",
    "url": "https://issuepcdn.baidupcs.com/issue/netdisk/yunguanjia/BaiduNetdisk_7.59.5.104.exe#/dl.7z",
    "hash": "7a28cbc4004521776759147a344989a0578d185b81f4f87f473286039bb3e976",
    "bin": "BaiduNetdisk.exe",
    "shortcuts": [
        [
            "BaiduNetdisk.exe",
            "BaiduNetdisk"
        ]
    ],
    "checkver": {
        "url": "https://yun.baidu.com/disk/cmsdata?platform=guanjia&page=1&num=2",
        "regex": "BaiduNetdisk_([\\d.]+).exe"
    },
    "autoupdate": {
        "url": "https://issuepcdn.baidupcs.com/issue/netdisk/yunguanjia/BaiduNetdisk_$version.exe#/dl.7z"
    },
    "notes": ""
}
